pdf_2_json_extractor/__init__.py
pdf_2_json_extractor/cli.py
pdf_2_json_extractor/config.py
pdf_2_json_extractor/exceptions.py
pdf_2_json_extractor/extractor.py
pdf_2_json_extractor-1.2.0.dist-info/licenses/LICENSE
pdf_2_json_extractor-1.2.0.dist-info/METADATA
pdf_2_json_extractor-1.2.0.dist-info/WHEEL
pdf_2_json_extractor-1.2.0.dist-info/entry_points.txt
pdf_2_json_extractor-1.2.0.dist-info/top_level.txt
pdf_2_json_extractor-1.2.0.dist-info/RECORD
