Metadata-Version: 2.4
Name: pdf_2_json_extractor
Version: 1.2.0
Summary: A high-performance PDF to JSON extraction library with layout-aware text extraction
Home-page: https://github.com/your-username/pdf_2_json_extractor
Author: Rushi Balapure
Author-email: pdf_2_json_extractor Team <rishibalapure12@gmail.com>
Maintainer-email: pdf_2_json_extractor Team <rishibalapure12@gmail.com>
License: Apache-2.0
Project-URL: Homepage, https://github.com/your-username/pdf_2_json_extractor
Project-URL: Documentation, https://github.com/your-username/pdf_2_json_extractor#readme
Project-URL: Repository, https://github.com/your-username/pdf_2_json_extractor
Project-URL: Bug Tracker, https://github.com/your-username/pdf_2_json_extractor/issues
Keywords: pdf,json,extraction,text,processing,layout,analysis
Classifier: Development Status :: 5 - Production/Stable
Classifier: Intended Audience :: Developers
Classifier: License :: OSI Approved :: Apache Software License
Classifier: Operating System :: OS Independent
Classifier: Programming Language :: Python :: 3
Classifier: Programming Language :: Python :: 3.10
Classifier: Programming Language :: Python :: 3.11
Classifier: Programming Language :: Python :: 3.12
Classifier: Programming Language :: Python :: 3.13
Classifier: Programming Language :: Python :: 3.14
Classifier: Topic :: Text Processing
Classifier: Topic :: Software Development :: Libraries :: Python Modules
Requires-Python: >=3.8
License-File: LICENSE
Requires-Dist: pymupdf>=1.24.0
Provides-Extra: dev
Requires-Dist: pytest; extra == "dev"
Requires-Dist: pytest-cov; extra == "dev"
Requires-Dist: mypy; extra == "dev"
Dynamic: author
Dynamic: home-page
Dynamic: license-file
Dynamic: requires-python
